dageo/__init__.py
dageo/data_assimilation.py
dageo/reservoir_simulator.py
dageo/utils.py
dageo/version.py
dageo-1.1.2.dist-info/licenses/LICENSE
dageo-1.1.2.dist-info/METADATA
dageo-1.1.2.dist-info/WHEEL
dageo-1.1.2.dist-info/top_level.txt
dageo-1.1.2.dist-info/RECORD
